MANIFEST.in
README.md
setup.py
jocular/RA_and_Dec.py
jocular/__init__.py
jocular/aligner.py
jocular/annotator.py
jocular/appearance.py
jocular/ascom.py
jocular/badpixelmap.py
jocular/calcs.py
jocular/calibrator.py
jocular/camera.py
jocular/capture.py
jocular/capturescript.py
jocular/catalogues.py
jocular/component.py
jocular/device.py
jocular/devicemanager.py
jocular/dso.py
jocular/exposurechooser.py
jocular/filterchooser.py
jocular/filterwheel.py
jocular/formwidgets.py
jocular/gradient.py
jocular/gui.py
jocular/image.py
jocular/info.py
jocular/jocular.py
jocular/metadata.py
jocular/metrics.py
jocular/monochrome.py
jocular/multispectral copy.py
jocular/multispectral.py
jocular/notes.py
jocular/objectio.py
jocular/observations.py
jocular/observinglist.py
jocular/platesolver.py
jocular/reticle.py
jocular/ring.py
jocular/session.py
jocular/settingsmanager.py
jocular/snapshotter.py
jocular/stacker.py
jocular/status.py
jocular/stretch.py
jocular/table.py
jocular/telescope.py
jocular/tooltip.py
jocular/uranography.py
jocular/utils.py
jocular/view.py
jocular/widgets.py
jocular/widgets_old.py
jocular.egg-info/PKG-INFO
jocular.egg-info/SOURCES.txt
jocular.egg-info/dependency_links.txt
jocular.egg-info/entry_points.txt
jocular.egg-info/requires.txt
jocular.egg-info/top_level.txt
jocular/cameras/__init__.py
jocular/cameras/ascomcamera.py
jocular/cameras/asicamera.py
jocular/cameras/genericcamera.py
jocular/cameras/simulatorcamera.py
jocular/cameras/sxcamera.py
jocular/cameras/ultrastar.py
jocular/cameras/watchedcamera.py
jocular/dsos/ACO.csv
jocular/dsos/Arp.csv
jocular/dsos/ArpMadore.csv
jocular/dsos/BN.csv
jocular/dsos/DN.csv
jocular/dsos/GC.csv
jocular/dsos/Hickson.csv
jocular/dsos/OCs_new.csv
jocular/dsos/PN.csv
jocular/dsos/RN.csv
jocular/dsos/Shakhbazian.csv
jocular/dsos/VV.csv
jocular/dsos/WBL.csv
jocular/dsos/distant_quasars.csv
jocular/dsos/flat_galaxies.csv
jocular/dsos/galaxies_IC.csv
jocular/dsos/galaxies_Messier.csv
jocular/dsos/galaxies_NGC.csv
jocular/dsos/missing_messiers.csv
jocular/dsos/pcg.csv
jocular/example_captures/Arp 186/L_1.fit
jocular/example_captures/Arp 186/L_10.fit
jocular/example_captures/Arp 186/L_11.fit
