Metadata-Version: 2.1
Name: jocular
Version: 0.5.6
Summary: A tool for near-live observation of astronomical objects
Home-page: https://transpy.eu.pythonanywhere.com/jocular/
Author: Martin Cooke
Author-email: martin.cooke.1917@gmail.com
License: UNKNOWN
Project-URL: Bug Reports, https://github.com/MartinCooke/jocular/issues
Project-URL: Source, https://github.com/MartinCooke/jocular
Keywords: astronomy
Platform: UNKNOWN
Classifier: Development Status :: 4 - Beta
Classifier: Intended Audience :: End Users/Desktop
Classifier: License :: OSI Approved :: MIT License
Classifier: Programming Language :: Python :: 3
Requires-Python: >=3.6
